[
    {
        "id": 1,
        "group": "a",
        "class_teacher": "Корнилов В.С.",
        "setting": {
            "class_grade": 5,
            "load": {
                "important": 1,
                "sport": 2,
                "history": 3,
                "math": 5,
                "russian": 9,
                "work": 2,
                "english": 3,
                "geography": 1,
                "biology": 2,
                "music": 1,
                "art": 1
            },
            "hours": 30
        }
    },
    {
        "id": 2,
        "group": "b",
        "class_teacher": "Юшкова Н.Н.",
        "setting": {
            "class_grade": 5,
            "load": {
                "important": 1,
                "sport": 2,
                "history": 3,
                "math": 5,
                "russian": 9,
                "work": 2,
                "english": 3,
                "geography": 1,
                "biology": 2,
                "music": 1,
                "art": 1
            },
            "hours": 30
        }
    },
    {
        "id": 3,
        "group": "c",
        "class_teacher": "Степанова В.А.",
        "setting": {
            "class_grade": 5,
            "load": {
                "important": 1,
                "sport": 2,
                "history": 3,
                "math": 5,
                "russian": 9,
                "work": 2,
                "english": 3,
                "geography": 1,
                "biology": 2,
                "music": 1,
                "art": 1
            },
            "hours": 30
        }
    }
]